kraken_record/kraken_attribute.py
kraken_record/kraken_record.py
kraken_record-0.0.4.dist-info/LICENSE.txt
kraken_record-0.0.4.dist-info/METADATA
kraken_record-0.0.4.dist-info/WHEEL
kraken_record-0.0.4.dist-info/top_level.txt
kraken_record-0.0.4.dist-info/RECORD
