Metadata-Version: 2.1
Name: kraken-record
Version: 0.0.4
Summary: Kraken schema helper
Home-page: https://github.com/tactik8/schema_model
Author: Tactik8
Author-email: info@tactik8.com
License: MIT
Platform: UNKNOWN
Classifier: License :: OSI Approved :: MIT License
Classifier: Programming Language :: Python :: 3
Classifier: Programming Language :: Python :: 3.8
